spx_sdk/__init__.py
spx_sdk/actions/__init__.py
spx_sdk/actions/action.py
spx_sdk/actions/actions.py
spx_sdk/actions/function_action.py
spx_sdk/actions/pip_install_action.py
spx_sdk/actions/set_action.py
spx_sdk/attributes/__init__.py
spx_sdk/attributes/attribute.py
spx_sdk/attributes/attributes.py
spx_sdk/attributes/resolve_attribute.py
spx_sdk/communication/__init__.py
spx_sdk/communication/protocol.py
spx_sdk/components/__init__.py
spx_sdk/components/component.py
spx_sdk/components/containter.py
spx_sdk/diagnostics/__init__.py
spx_sdk/diagnostics/bus.py
spx_sdk/diagnostics/context.py
spx_sdk/diagnostics/diag_types.py
spx_sdk/diagnostics/faults.py
spx_sdk/diagnostics/guard.py
spx_sdk/hooks/__init__.py
spx_sdk/hooks/hooks.py
spx_sdk/hooks/refresh.py
spx_sdk/imports/__init__.py
spx_sdk/imports/python_file.py
spx_sdk/logic/__init__.py
spx_sdk/logic/conditions.py
spx_sdk/model/__init__.py
spx_sdk/model/model_base.py
spx_sdk/model/polling.py
spx_sdk/model/timer.py
spx_sdk/registry.py
spx_sdk/validation/__init__.py
spx_sdk/validation/_jsonschema_backend.py
spx_sdk/validation/decorators.py
spx_sdk/validation/engine.py
spx_sdk/validation/errors.py
spx_sdk-1.0.0.dist-info/METADATA
spx_sdk-1.0.0.dist-info/WHEEL
spx_sdk-1.0.0.dist-info/licenses/LICENSE
spx_sdk-1.0.0.dist-info/RECORD
