Metadata-Version: 2.4
Name: spx-sdk
Version: 1.0.0
Summary: A Python library for managing and loading class instances from modules and YAML configurations.
License: MIT
License-File: LICENSE
Author: Aleksander Stanik
Author-email: aleksander.stanik@hammerheadesengineers.com
Requires-Python: >=3.9,<4.0
Classifier: License :: OSI Approved :: MIT License
Classifier: Programming Language :: Python :: 3
Classifier: Programming Language :: Python :: 3.9
Classifier: Programming Language :: Python :: 3.10
Classifier: Programming Language :: Python :: 3.11
Classifier: Programming Language :: Python :: 3.12
Classifier: Programming Language :: Python :: 3.13
Classifier: Programming Language :: Python :: 3.14
Requires-Dist: PyYAML
Requires-Dist: fastapi
Requires-Dist: httpx
Requires-Dist: jsonschema (>=4.21,<5)
Requires-Dist: uvicorn
